audit_tools/__init__.py
audit_tools/core/__init__.py
audit_tools/core/errors.py
audit_tools/core/session.py
audit_tools/core/utils/__init__.py
audit_tools/core/utils/converters.py
audit_tools/core/utils/file_manager.py
audit_tools/core/utils/logger.py
audit_tools/core/utils/scanner.py
audit_tools/sessionmanager.py
audit_tools-0.1.14.dist-info/WHEEL
audit_tools-0.1.14.dist-info/METADATA
audit_tools-0.1.14.dist-info/RECORD
