Metadata-Version: 2.1
Name: audit-tools
Version: 0.1.14
Summary: Auditing tools for Cova POS files
Home-page: https://github.com/JakePIXL/audit-tools
Author: JakePIXL
Author-email: jakewjevans@gmail.com
Requires-Python: >=3.8,<4.0
Classifier: Programming Language :: Python :: 3
Classifier: Programming Language :: Python :: 3.10
Classifier: Programming Language :: Python :: 3.8
Classifier: Programming Language :: Python :: 3.9
Requires-Dist: numpy (>=1.22.3,<2.0.0)
Requires-Dist: openpyxl (>=3.0.9,<4.0.0)
Requires-Dist: pandas (>=1.4.2,<2.0.0)
Requires-Dist: pydantic (>=1.9.0,<2.0.0)
Requires-Dist: rich (>=12.4.1,<13.0.0)
Project-URL: Repository, https://github.com/JakePIXL/audit-tools
